LICENSE
setup.py
django_okta_sso/__init__.py
django_okta_sso/apps.py
django_okta_sso/backend.py
django_okta_sso/conf.py
django_okta_sso/decorators.py
django_okta_sso/exceptions.py
django_okta_sso/middleware.py
django_okta_sso/tokens.py
django_okta_sso/urls.py
django_okta_sso/views.py
django_okta_sso.egg-info/PKG-INFO
django_okta_sso.egg-info/SOURCES.txt
django_okta_sso.egg-info/dependency_links.txt
django_okta_sso.egg-info/top_level.txt