Metadata-Version: 2.1
Name: django-okta-sso
Version: 0.1.5
Summary: Okta SSO package for Django that still uses Django users, groups, and permissions
Home-page: https://github.com/crunchmasterdeluxe/django-okta-sso
Author: Andy Gannaway
Author-email: iamandycmd@gmail.com
License: BSD 2-clause
Classifier: Development Status :: 4 - Beta
Classifier: Intended Audience :: Science/Research
Classifier: License :: OSI Approved :: BSD License
Classifier: Operating System :: POSIX :: Linux
Classifier: Programming Language :: Python :: 3.6
Classifier: Programming Language :: Python :: 3.8
Classifier: Programming Language :: Python :: 3.9
License-File: LICENSE
